Workbook

Sheet Summary
A1: Soulink pre-seed: summary
A2: All figures are estimates from the Assumptions tab (₹ lakh unless noted). Change the blue cells there and this page updates.
A3: The round
A4: Raise (₹ lakh) | B4: =Assumptions!$B$5 -> 150
A5: Pre-money valuation (₹ lakh) | B5: =Assumptions!$B$6 -> 1050
A6: Post-money valuation (₹ lakh) | B6: =B4+B5 -> 1200
A7: Investors own | B7: =IFERROR(B4/B6,0) -> 0.125
A8: Runway
A9: Months the round lasts (cash stays above zero) | B9: =COUNTIF(Monthly!B24:Y24,">0") -> 24
A10: Average monthly burn, months 1–12 | B10: =AVERAGE(Monthly!B23:M23) -> 7.0900724
A11: Cash left after month 18 | B11: =Monthly!S24 -> 31.970662
A12: Milestones
A13: MAU at month 12 | B13: =Monthly!M5 -> 48902.39
A14: MAU at month 18 | B14: =Monthly!S5 -> 96524.647
A15: MAU at month 24 | B15: =Monthly!Y5 -> 190522.54
A16: Net revenue in month 18 (₹ lakh / month) | B16: =Monthly!S13 -> 4.5095478
A17: Net revenue, months 13–24 total | B17: =SUM(Monthly!N13:Y13) -> 60.963234
A18: Revenue as % of costs in month 24 | B18: =IFERROR(Monthly!Y13/Monthly!Y21,0) -> 0.79170215
A19: Revenue mix, months 1–24
A20: Ads | B20: =SUM(Monthly!B8:Y8) -> 18.359525
A21: Spread around | B21: =SUM(Monthly!B9:Y9) -> 7.3639938
A22: Premium | B22: =SUM(Monthly!B10:Y10) -> 18.059064
A23: Brand partnerships + events | B23: =SUM(Monthly!B11:Y11) -> 32.00125

Sheet Use of funds
A1: Use of funds: first 18 months (₹ lakh)
A3: Bucket | B3: ₹ lakh | C3: Share
A4: Team (product, engineering, design, community, partnerships) | B4: =SUM(Monthly!B16:S16) -> 95.6 | C4: =IFERROR(B4/$B$9,0) -> 0.63133032
A5: Cloud and AI services | B5: =SUM(Monthly!B17:S17) -> 15.326276 | C5: =IFERROR(B5/$B$9,0) -> 0.10121279
A6: Marketing (campus events, creators) | B6: =SUM(Monthly!B18:S18) -> 27 | C6: =IFERROR(B6/$B$9,0) -> 0.17830459
A7: Legal, accounting, tools | B7: =SUM(Monthly!B19:S19) -> 9 | C7: =IFERROR(B7/$B$9,0) -> 0.059434863
A8: One-time setup | B8: =SUM(Monthly!B20:S20) -> 4.5 | C8: =IFERROR(B8/$B$9,0) -> 0.029717432
A9: Total spend, months 1–18 | B9: =SUM(B4:B8) -> 151.42628
A10: Less: revenue earned in months 1–18 | B10: =SUM(Monthly!B13:S13) -> 33.396938
A11: Net cash needed for 18 months | B11: =B9-B10 -> 118.02934
A12: Raise | B12: =Assumptions!$B$5 -> 150
A13: Buffer left at month 18 | B13: =B12-B11 -> 31.970662

Sheet Assumptions
A1: Soulink: pre-seed financial model
A2: Money in ₹ lakh unless a row says otherwise (1 lakh = ₹1,00,000; 100 lakh = ₹1 crore). Blue = inputs you can change; yellow = key levers. Every figure is a planning estimate, not actual results.
A4: The round
A5: Amount to raise (₹ lakh) | B5: 150 | C5: Proposed ask: ₹1.5 crore, inside the ₹50 lakh–₹2 crore range you chose.
A6: Pre-money valuation (₹ lakh) | B6: 1050 | C6: Opening position, negotiable. Pre-product-market-fit consumer apps in India usually raise pre-seed at roughly ₹8–20 crore post-money.
A7: Users (monthly active users, MAU)
A8: MAU in month 1 | B8: 2000 | C8: Invite-only launch in Hyderabad colleges and young professionals.
A9: Monthly MAU growth, months 2–6 | B9: 0.45 | C9: Campus-by-campus launch.
A10: Monthly MAU growth, months 7–12 | B10: 0.25
A11: Monthly MAU growth, months 13–24 | B11: 0.12 | C11: Second and third city.
A12: Revenue drivers
A13: Ad impressions per MAU per month | B13: 60 | C13: Sponsored cards: every 4th Home post, every 5th Spark, sponsored Argue.
A14: Ad fill rate (share of ad slots sold) | B14: 0.4 | C14: Direct-sold to brands by the team; no ad network.
A15: Ad eCPM (₹ per 1,000 impressions) | B15: 50 | C15: Assumption for direct-sold youth-brand placements in India; check with your first 3 brands.
A16: Ads start in month | B16: 4
A17: Spread around: share of MAU who buy one per month | B17: 0.004 | C17: Boost plans ₹49 / ₹129 / ₹249.
A18: Spread around: average spend (₹) | B18: 120 | C18: Mix of the three plans.
A19: Spread around starts in month | B19: 3 | C19: Needs Razorpay (company KYC).
A20: Premium: share of MAU paying | B20: 0.008 | C20: You expect Premium to grow slowly, so this is kept low.
A21: Premium price per month (₹) | B21: 149 | C21: Assumption; set to your real Premium price.
A22: Premium starts in month | B22: 6
A23: Brand partnerships + events, first month (₹ lakh) | B23: 0.5 | C23: Campus events, college fests, brand challenges on Sparks / Open Mic.
A24: Brand partnerships + events start in month | B24: 4
A25: Brand partnerships + events monthly growth | B25: 0.1
A26: Payment and app-store fees on Premium + Spread | B26: 0.1 | C26: Blend of Razorpay on web (~2%) and app-store fees on phones.
A27: Costs
A28: Founders (2), total per month (₹ lakh) | B28: 1.5 | C28: Below-market founder salaries.
A29: Engineers (2), total per month (₹ lakh) | B29: 2 | C29: Hyderabad full-stack / mobile.
A30: Designer, per month (₹ lakh) | B30: 0.7 | C30: From month 2.
A31: Campus / community lead, per month (₹ lakh) | B31: 0.5
A32: Brand partnerships manager, per month (₹ lakh) | B32: 0.9 | C32: From month 6; sells ads, events and brand deals.
A33: Cloud: fixed per month (₹ lakh) | B33: 0.3 | C33: Database, hosting, AI services (Soulmoji, translator, Argue).
A34: Cloud: cost per MAU per month (₹) | B34: 1.5 | C34: Video (Sparks) is the big driver.
A35: Marketing: campus events, creators (₹ lakh / month) | B35: 1.5 | C35: Koo spent most of its money on paid promotion and shut down in 2024; keep this lean.
A36: Legal, accounting, tools (₹ lakh / month) | B36: 0.5
A37: One-time setup in month 1 (₹ lakh) | B37: 4.5 | C37: Company, trademark, DPIIT, laptops / test phones.

Sheet Monthly
A1: Monthly plan (₹ lakh)
A3: Month | B3: 1 | C3: 2 | D3: 3 | E3: 4 | F3: 5 | G3: 6 | H3: 7 | I3: 8 | J3: 9 | K3: 10 | L3: 11 | M3: 12 | N3: 13 | O3: 14 | P3: 15 | Q3: 16 | R3: 17 | S3: 18 | T3: 19 | U3: 20 | V3: 21 | W3: 22 | X3: 23 | Y3: 24
A4: Users
A5: Monthly active users (MAU) | B5: =Assumptions!$B$8 -> 2000 | C5: =B5*(1+IF(C$3<=6,Assumptions!$B$9,IF(C$3<=12,Assumptions!$B$10,Assumptions!$B$11))) -> 2900 | D5: =C5*(1+IF(D$3<=6,Assumptions!$B$9,IF(D$3<=12,Assumptions!$B$10,Assumptions!$B$11))) -> 4205 | E5: =D5*(1+IF(E$3<=6,Assumptions!$B$9,IF(E$3<=12,Assumptions!$B$10,Assumptions!$B$11))) -> 6097.25 | F5: =E5*(1+IF(F$3<=6,Assumptions!$B$9,IF(F$3<=12,Assumptions!$B$10,Assumptions!$B$11))) -> 8841.0125 | G5: =F5*(1+IF(G$3<=6,Assumptions!$B$9,IF(G$3<=12,Assumptions!$B$10,Assumptions!$B$11))) -> 12819.468 | H5: =G5*(1+IF(H$3<=6,Assumptions!$B$9,IF(H$3<=12,Assumptions!$B$10,Assumptions!$B$11))) -> 16024.335 | I5: =H5*(1+IF(I$3<=6,Assumptions!$B$9,IF(I$3<=12,Assumptions!$B$10,Assumptions!$B$11))) -> 20030.419 | J5: =I5*(1+IF(J$3<=6,Assumptions!$B$9,IF(J$3<=12,Assumptions!$B$10,Assumptions!$B$11))) -> 25038.024 | ... Y5: =X5*(1+IF(Y$3<=6,Assumptions!$B$9,IF(Y$3<=12,Assumptions!$B$10,Assumptions!$B$11))) -> 190522.54
A7: Revenue
A8: Ads (feed, Spark ads, sponsored Argue) | B8: =IF(B$3>=Assumptions!$B$16,B5*Assumptions!$B$13*Assumptions!$B$14*Assumptions!$B$15/1000/100000,0) -> 0 | C8: =IF(C$3>=Assumptions!$B$16,C5*Assumptions!$B$13*Assumptions!$B$14*Assumptions!$B$15/1000/100000,0) -> 0 | D8: =IF(D$3>=Assumptions!$B$16,D5*Assumptions!$B$13*Assumptions!$B$14*Assumptions!$B$15/1000/100000,0) -> 0 | E8: =IF(E$3>=Assumptions!$B$16,E5*Assumptions!$B$13*Assumptions!$B$14*Assumptions!$B$15/1000/100000,0) -> 0.073167 | F8: =IF(F$3>=Assumptions!$B$16,F5*Assumptions!$B$13*Assumptions!$B$14*Assumptions!$B$15/1000/100000,0) -> 0.10609215 | G8: =IF(G$3>=Assumptions!$B$16,G5*Assumptions!$B$13*Assumptions!$B$14*Assumptions!$B$15/1000/100000,0) -> 0.15383362 | H8: =IF(H$3>=Assumptions!$B$16,H5*Assumptions!$B$13*Assumptions!$B$14*Assumptions!$B$15/1000/100000,0) -> 0.19229202 | I8: =IF(I$3>=Assumptions!$B$16,I5*Assumptions!$B$13*Assumptions!$B$14*Assumptions!$B$15/1000/100000,0) -> 0.24036503 | ... Y8: =IF(Y$3>=Assumptions!$B$16,Y5*Assumptions!$B$13*Assumptions!$B$14*Assumptions!$B$15/1000/100000,0) -> 2.2862704
A9: Spread around | B9: =IF(B$3>=Assumptions!$B$19,B5*Assumptions!$B$17*Assumptions!$B$18/100000,0) -> 0 | C9: =IF(C$3>=Assumptions!$B$19,C5*Assumptions!$B$17*Assumptions!$B$18/100000,0) -> 0 | D9: =IF(D$3>=Assumptions!$B$19,D5*Assumptions!$B$17*Assumptions!$B$18/100000,0) -> 0.020184 | E9: =IF(E$3>=Assumptions!$B$19,E5*Assumptions!$B$17*Assumptions!$B$18/100000,0) -> 0.0292668 | F9: =IF(F$3>=Assumptions!$B$19,F5*Assumptions!$B$17*Assumptions!$B$18/100000,0) -> 0.04243686 | G9: =IF(G$3>=Assumptions!$B$19,G5*Assumptions!$B$17*Assumptions!$B$18/100000,0) -> 0.061533447 | H9: =IF(H$3>=Assumptions!$B$19,H5*Assumptions!$B$17*Assumptions!$B$18/100000,0) -> 0.076916809 | I9: =IF(I$3>=Assumptions!$B$19,I5*Assumptions!$B$17*Assumptions!$B$18/100000,0) -> 0.096146011 | ... Y9: =IF(Y$3>=Assumptions!$B$19,Y5*Assumptions!$B$17*Assumptions!$B$18/100000,0) -> 0.91450818
A10: Premium | B10: =IF(B$3>=Assumptions!$B$22,B5*Assumptions!$B$20*Assumptions!$B$21/100000,0) -> 0 | C10: =IF(C$3>=Assumptions!$B$22,C5*Assumptions!$B$20*Assumptions!$B$21/100000,0) -> 0 | D10: =IF(D$3>=Assumptions!$B$22,D5*Assumptions!$B$20*Assumptions!$B$21/100000,0) -> 0 | E10: =IF(E$3>=Assumptions!$B$22,E5*Assumptions!$B$20*Assumptions!$B$21/100000,0) -> 0 | F10: =IF(F$3>=Assumptions!$B$22,F5*Assumptions!$B$20*Assumptions!$B$21/100000,0) -> 0 | G10: =IF(G$3>=Assumptions!$B$22,G5*Assumptions!$B$20*Assumptions!$B$21/100000,0) -> 0.15280806 | H10: =IF(H$3>=Assumptions!$B$22,H5*Assumptions!$B$20*Assumptions!$B$21/100000,0) -> 0.19101008 | I10: =IF(I$3>=Assumptions!$B$22,I5*Assumptions!$B$20*Assumptions!$B$21/100000,0) -> 0.23876259 | ... Y10: =IF(Y$3>=Assumptions!$B$22,Y5*Assumptions!$B$20*Assumptions!$B$21/100000,0) -> 2.2710286
A11: Brand partnerships + events | B11: =IF(B$3>=Assumptions!$B$24,Assumptions!$B$23*(1+Assumptions!$B$25)^(B$3-Assumptions!$B$24),0) -> 0 | C11: =IF(C$3>=Assumptions!$B$24,Assumptions!$B$23*(1+Assumptions!$B$25)^(C$3-Assumptions!$B$24),0) -> 0 | D11: =IF(D$3>=Assumptions!$B$24,Assumptions!$B$23*(1+Assumptions!$B$25)^(D$3-Assumptions!$B$24),0) -> 0 | E11: =IF(E$3>=Assumptions!$B$24,Assumptions!$B$23*(1+Assumptions!$B$25)^(E$3-Assumptions!$B$24),0) -> 0.5 | F11: =IF(F$3>=Assumptions!$B$24,Assumptions!$B$23*(1+Assumptions!$B$25)^(F$3-Assumptions!$B$24),0) -> 0.55 | G11: =IF(G$3>=Assumptions!$B$24,Assumptions!$B$23*(1+Assumptions!$B$25)^(G$3-Assumptions!$B$24),0) -> 0.605 | H11: =IF(H$3>=Assumptions!$B$24,Assumptions!$B$23*(1+Assumptions!$B$25)^(H$3-Assumptions!$B$24),0) -> 0.6655 | I11: =IF(I$3>=Assumptions!$B$24,Assumptions!$B$23*(1+Assumptions!$B$25)^(I$3-Assumptions!$B$24),0) -> 0.73205 | ... Y11: =IF(Y$3>=Assumptions!$B$24,Assumptions!$B$23*(1+Assumptions!$B$25)^(Y$3-Assumptions!$B$24),0) -> 3.36375
A12: Less: payment / app-store fees | B12: =-(B9+B10)*Assumptions!$B$26 -> 0 | C12: =-(C9+C10)*Assumptions!$B$26 -> 0 | D12: =-(D9+D10)*Assumptions!$B$26 -> -0.0020184 | E12: =-(E9+E10)*Assumptions!$B$26 -> -0.00292668 | F12: =-(F9+F10)*Assumptions!$B$26 -> -0.004243686 | G12: =-(G9+G10)*Assumptions!$B$26 -> -0.021434151 | H12: =-(H9+H10)*Assumptions!$B$26 -> -0.026792688 | I12: =-(I9+I10)*Assumptions!$B$26 -> -0.03349086 | ... Y12: =-(Y9+Y10)*Assumptions!$B$26 -> -0.31855368
A13: Net revenue | B13: =SUM(B8:B12) -> 0 | C13: =SUM(C8:C12) -> 0 | D13: =SUM(D8:D12) -> 0.0181656 | E13: =SUM(E8:E12) -> 0.59950712 | F13: =SUM(F8:F12) -> 0.69428532 | G13: =SUM(G8:G12) -> 0.95174097 | H13: =SUM(H8:H12) -> 1.0989262 | I13: =SUM(I8:I12) -> 1.2738328 | ... Y13: =SUM(Y8:Y12) -> 8.5170036
A15: Costs
A16: Team | B16: =Assumptions!$B$28+Assumptions!$B$29+Assumptions!$B$31+IF(B$3>=2,Assumptions!$B$30,0)+IF(B$3>=6,Assumptions!$B$32,0) -> 4 | C16: =Assumptions!$B$28+Assumptions!$B$29+Assumptions!$B$31+IF(C$3>=2,Assumptions!$B$30,0)+IF(C$3>=6,Assumptions!$B$32,0) -> 4.7 | D16: =Assumptions!$B$28+Assumptions!$B$29+Assumptions!$B$31+IF(D$3>=2,Assumptions!$B$30,0)+IF(D$3>=6,Assumptions!$B$32,0) -> 4.7 | E16: =Assumptions!$B$28+Assumptions!$B$29+Assumptions!$B$31+IF(E$3>=2,Assumptions!$B$30,0)+IF(E$3>=6,Assumptions!$B$32,0) -> 4.7 | F16: =Assumptions!$B$28+Assumptions!$B$29+Assumptions!$B$31+IF(F$3>=2,Assumptions!$B$30,0)+IF(F$3>=6,Assumptions!$B$32,0) -> 4.7 | G16: =Assumptions!$B$28+Assumptions!$B$29+Assumptions!$B$31+IF(G$3>=2,Assumptions!$B$30,0)+IF(G$3>=6,Assumptions!$B$32,0) -> 5.6 | H16: =Assumptions!$B$28+Assumptions!$B$29+Assumptions!$B$31+IF(H$3>=2,Assumptions!$B$30,0)+IF(H$3>=6,Assumptions!$B$32,0) -> 5.6 | I16: =Assumptions!$B$28+Assumptions!$B$29+Assumptions!$B$31+IF(I$3>=2,Assumptions!$B$30,0)+IF(I$3>=6,Assumptions!$B$32,0) -> 5.6 | ... Y16: =Assumptions!$B$28+Assumptions!$B$29+Assumptions!$B$31+IF(Y$3>=2,Assumptions!$B$30,0)+IF(Y$3>=6,Assumptions!$B$32,0) -> 5.6
A17: Cloud and AI services | B17: =Assumptions!$B$33+B5*Assumptions!$B$34/100000 -> 0.33 | C17: =Assumptions!$B$33+C5*Assumptions!$B$34/100000 -> 0.3435 | D17: =Assumptions!$B$33+D5*Assumptions!$B$34/100000 -> 0.363075 | E17: =Assumptions!$B$33+E5*Assumptions!$B$34/100000 -> 0.39145875 | F17: =Assumptions!$B$33+F5*Assumptions!$B$34/100000 -> 0.43261519 | G17: =Assumptions!$B$33+G5*Assumptions!$B$34/100000 -> 0.49229202 | H17: =Assumptions!$B$33+H5*Assumptions!$B$34/100000 -> 0.54036503 | I17: =Assumptions!$B$33+I5*Assumptions!$B$34/100000 -> 0.60045628 | ... Y17: =Assumptions!$B$33+Y5*Assumptions!$B$34/100000 -> 3.1578381
A18: Marketing (campus events, creators) | B18: =Assumptions!$B$35 -> 1.5 | C18: =Assumptions!$B$35 -> 1.5 | D18: =Assumptions!$B$35 -> 1.5 | E18: =Assumptions!$B$35 -> 1.5 | F18: =Assumptions!$B$35 -> 1.5 | G18: =Assumptions!$B$35 -> 1.5 | H18: =Assumptions!$B$35 -> 1.5 | I18: =Assumptions!$B$35 -> 1.5 | ... Y18: =Assumptions!$B$35 -> 1.5
A19: Legal, accounting, tools | B19: =Assumptions!$B$36 -> 0.5 | C19: =Assumptions!$B$36 -> 0.5 | D19: =Assumptions!$B$36 -> 0.5 | E19: =Assumptions!$B$36 -> 0.5 | F19: =Assumptions!$B$36 -> 0.5 | G19: =Assumptions!$B$36 -> 0.5 | H19: =Assumptions!$B$36 -> 0.5 | I19: =Assumptions!$B$36 -> 0.5 | ... Y19: =Assumptions!$B$36 -> 0.5
A20: One-time setup | B20: =IF(B$3=1,Assumptions!$B$37,0) -> 4.5 | C20: =IF(C$3=1,Assumptions!$B$37,0) -> 0 | D20: =IF(D$3=1,Assumptions!$B$37,0) -> 0 | E20: =IF(E$3=1,Assumptions!$B$37,0) -> 0 | F20: =IF(F$3=1,Assumptions!$B$37,0) -> 0 | G20: =IF(G$3=1,Assumptions!$B$37,0) -> 0 | H20: =IF(H$3=1,Assumptions!$B$37,0) -> 0 | I20: =IF(I$3=1,Assumptions!$B$37,0) -> 0 | ... Y20: =IF(Y$3=1,Assumptions!$B$37,0) -> 0
A21: Total costs | B21: =SUM(B16:B20) -> 10.83 | C21: =SUM(C16:C20) -> 7.0435 | D21: =SUM(D16:D20) -> 7.063075 | E21: =SUM(E16:E20) -> 7.0914588 | F21: =SUM(F16:F20) -> 7.1326152 | G21: =SUM(G16:G20) -> 8.092292 | H21: =SUM(H16:H20) -> 8.140365 | I21: =SUM(I16:I20) -> 8.2004563 | ... Y21: =SUM(Y16:Y20) -> 10.757838
A23: Net burn (costs − revenue) | B23: =B21-B13 -> 10.83 | C23: =C21-C13 -> 7.0435 | D23: =D21-D13 -> 7.0449094 | E23: =E21-E13 -> 6.4919516 | F23: =F21-F13 -> 6.4383299 | G23: =G21-G13 -> 7.140551 | H23: =H21-H13 -> 7.0414388 | I23: =I21-I13 -> 6.9266235 | ... Y23: =Y21-Y13 -> 2.2408345
A24: Cash left from the round | B24: =Assumptions!$B$5-B23 -> 139.17 | C24: =B24-C23 -> 132.1265 | D24: =C24-D23 -> 125.08159 | E24: =D24-E23 -> 118.58964 | F24: =E24-F23 -> 112.15131 | G24: =F24-G23 -> 105.01076 | H24: =G24-H23 -> 97.969319 | I24: =H24-I23 -> 91.042696 | J24: =I24-J23 -> 84.249609 | ... Y24: =X24-Y23 -> 11.255545

Sheet Sources
A1: Market context used in the deck
A3: India internet users | B3: ~1.03 billion (70% of people), Oct 2025 data | C3: DataReportal, Digital 2026: India — https://datareportal.com/reports/digital-2026-india
A4: India social media user identities | B4: ~500 million; 455 million aged 18+ | C4: DataReportal, Digital 2026: India
A5: Instagram ad reach in India | B5: ~481 million | C5: DataReportal, Digital 2026: India
A6: India total ad market | B6: ₹1,55,105 crore (2025); ₹1,74,605 crore projected 2026 | C6: Pitch Madison Advertising Report via exchange4media — https://www.exchange4media.com/digital-news/indias-ad-economy-crosses-digital-milestone-64-share-projected-for-2026-pmar-152319.html
A7: Digital share of ad market | B7: 60% (2025) → 64% projected (2026) | C7: Same as above
A8: Social media ad spend in India | B8: ₹12,143 crore in 2025, +16% | C8: Same as above
A9: Startup India Seed Fund Scheme | B9: Grant up to ₹20 lakh; debt / convertible up to ₹50 lakh; via incubators; DPIIT recognition, under 2 years old | C9: https://seedfund.startupindia.gov.in (summary from incorpx.io; verify on the official portal)
A10: Koo shutdown (2024) | B10: Raised ~$70M; most of a $30M round went to paid promotion; revenue negligible | C10: Finshots — https://finshots.in/archive/a-postmortem-of-koo/ ; TechCrunch 2 Jul 2024
